alu.sv
module alu(
    input logic [31:0] a, b, 
    input logic [3:0] alu_contr,
    output logic [31:0] result,
    output logic zero
);
    //riscv does not handle overflow
    typedef enum logic [3:0]{
        ALU_ADD: 4'b0000;
        ALU_SUB: 4'b0001;
        ALU_AND: 4'b0010;
        ALU_OR: 4'b0011;
        ALU_XOR: 4'b0100;
        ALU_SLT: 4'b0101; //set less than (signed)
        ALU_SLTU: 4'b0110; //set less than (unsigned)
        ALU_SLL: 4'b0111; //logical left shift *all shifts based on bottom 5 bits of operand 2
        ALU_SRL: 4'b1000; //logical right shift
        ALU_SRA: 4'b1001; //arithmetic right shift
    } type_name_t;
    
    always_comb begin
        case (alu_contr) 
            ALU_ADD: result = a + b;
            ALU_SUB: result = a - b;
            ALU_AND: result = a & b;
            ALU_OR: result = a | b;
            ALU_XOR: result = a ^ b;
            ALU_SLT: result = ($signed(a) < $signed(b)) ? 32'd1 : '0;
            ALU_SLTU: result = (a < b) ? 32'd1 : '0;
            ALU_SLL: result = a << b[4:0];
            ALU_SRL: result = a >> b [4:0];
            ALU_SRA: result = $signed(a) >>> b[4:0]; // signed needed bc >>> only works if operand is explicitly signed
        endcase

    end

    assign zero = result ==32'b0;


endmodule

tb_alu.sv
        `timescale 1ns / 10ps
        /* verilator coverage_off */

        module tb_alu ();

            initial begin
                $dumpfile("waveform.vcd");
                $dumpvars;
            end

            
            // DUT interface signals
            logic [31:0] a, b, result;
            logic [3:0] alu_contr;
            logic zero;

            

            alu DUT (
                .a(a),
                .b(b),
                .alu_contr(alu_contr),
                .result(result),
                .zero(zero)
            );
            typedef struct {
                logic [3:0] alu_op;
                logic [31:0] a,b;
                logic [31:0] expected_result
                logic expected_zero;
            } test_vector_t;

            test_vector_t test_vectors[]='{
                '{4'b0000,32'd10,32'd20,32'd30,1'b0}//ADD
            };
            initial begin
                // Initialize stimulus lines
                n_rst      = 1'b1;
                reg_write  = 1'b0;
                read_reg1  = '0;
                read_reg2  = '0;
                write_reg  = '0;
                write_data = '0;

                // Apply reset sequence
                reset_dut();

                // Verify all 32 registers retain 0 after reset release
                $display("--- Testing Post-Reset Zero State ---");
                for (int i = 0; i < 32; i = i + 2) begin
                    read_register(5'(i), 5'(i+1), 32'h0, 32'h0);
                end
                
                @(negedge clk);

                $display("--- Testing register zero after write ---");
                write_register(5'd0,32'hFFFF_FFFF);
                read_register(5'd0,5'd0,32'h0,32'h0);

                @(negedge clk);
                $display("--- Testing Indepedent Port ---");
                write_register(5'd1,32'hABCD_DBCA);
                write_register(5'd2,32'hEFDC_BCBC);

                read_register(5'd1,5'd2,32'hABCD_DBCA,32'hEFDC_BCBC);
                read_register(5'd2,5'd1,32'hEFDC_BCBC,32'hABCD_DBCA);

                #(CLK_PERIOD * 2);

                
                $finish;
            end

        endmodule

        /* verilator coverage_on */

waveform.vcd
$date
	Tue Sep 22 20:46:04 2026
$end
$version
	Questa Altera Starter FPGA Edition Version 2025.2
$end
$timescale
	10ps
$end

$scope module tb_alu $end
$var reg 32 ! a [31:0] $end
$var reg 32 " b [31:0] $end
$var reg 32 # result [31:0] $end
$var reg 4 $ alu_contr [3:0] $end
$var reg 1 % zero $end

$scope module DUT $end
$var wire 1 & a [31] $end
$var wire 1 ' a [30] $end
$var wire 1 ( a [29] $end
$var wire 1 ) a [28] $end
$var wire 1 * a [27] $end
$var wire 1 + a [26] $end
$var wire 1 , a [25] $end
$var wire 1 - a [24] $end
$var wire 1 . a [23] $end
$var wire 1 / a [22] $end
$var wire 1 0 a [21] $end
$var wire 1 1 a [20] $end
$var wire 1 2 a [19] $end
$var wire 1 3 a [18] $end
$var wire 1 4 a [17] $end
$var wire 1 5 a [16] $end
$var wire 1 6 a [15] $end
$var wire 1 7 a [14] $end
$var wire 1 8 a [13] $end
$var wire 1 9 a [12] $end
$var wire 1 : a [11] $end
$var wire 1 ; a [10] $end
$var wire 1 < a [9] $end
$var wire 1 = a [8] $end
$var wire 1 > a [7] $end
$var wire 1 ? a [6] $end
$var wire 1 @ a [5] $end
$var wire 1 A a [4] $end
$var wire 1 B a [3] $end
$var wire 1 C a [2] $end
$var wire 1 D a [1] $end
$var wire 1 E a [0] $end
$var wire 1 F b [31] $end
$var wire 1 G b [30] $end
$var wire 1 H b [29] $end
$var wire 1 I b [28] $end
$var wire 1 J b [27] $end
$var wire 1 K b [26] $end
$var wire 1 L b [25] $end
$var wire 1 M b [24] $end
$var wire 1 N b [23] $end
$var wire 1 O b [22] $end
$var wire 1 P b [21] $end
$var wire 1 Q b [20] $end
$var wire 1 R b [19] $end
$var wire 1 S b [18] $end
$var wire 1 T b [17] $end
$var wire 1 U b [16] $end
$var wire 1 V b [15] $end
$var wire 1 W b [14] $end
$var wire 1 X b [13] $end
$var wire 1 Y b [12] $end
$var wire 1 Z b [11] $end
$var wire 1 [ b [10] $end
$var wire 1 \ b [9] $end
$var wire 1 ] b [8] $end
$var wire 1 ^ b [7] $end
$var wire 1 _ b [6] $end
$var wire 1 ` b [5] $end
$var wire 1 a b [4] $end
$var wire 1 b b [3] $end
$var wire 1 c b [2] $end
$var wire 1 d b [1] $end
$var wire 1 e b [0] $end
$var wire 1 f alu_contr [3] $end
$var wire 1 g alu_contr [2] $end
$var wire 1 h alu_contr [1] $end
$var wire 1 i alu_contr [0] $end
$var reg 32 j result [31:0] $end
$var reg 1 k zero $end
$upscope $end
$upscope $end

$scope begin std $end
$upscope $end
$enddefinitions $end
#0
$dumpvars
b1010 !
b10100 "
b11110 #
b0 $
0%
b11110 j
0k
0i
0h
0g
0f
0e
0d
1c
0b
1a
0`
0_
0^
0]
0\
0[
0Z
0Y
0X
0W
0V
0U
0T
0S
0R
0Q
0P
0O
0N
0M
0L
0K
0J
0I
0H
0G
0F
0E
1D
0C
1B
0A
0@
0?
0>
0=
0<
0;
0:
09
08
07
06
05
04
03
02
01
00
0/
0.
0-
0,
0+
0*
0)
0(
0'
0&
$end
#1000
b1 $
b10100 !
b1010 "
1d
0c
1b
0a
0D
1C
0B
1A
1i
b1010 j
b1010 #
#2000
b0 $
b11111111111111111111111111111111 !
b1 "
1e
0d
0b
1E
1D
1B
1@
1?
1>
1=
1<
1;
1:
19
18
17
16
15
14
13
12
11
10
1/
1.
1-
1,
1+
1*
1)
1(
1'
1&
0i
b0 j
b0 #
1k
1%
#3000
b10 $
b11111111111111111111111111110000 !
b11111111111111111111000011110000 "
0e
1a
1`
1_
1^
1Y
1X
1W
1V
1U
1T
1S
1R
1Q
1P
1O
1N
1M
1L
1K
1J
1I
1H
1G
1F
0E
0D
0C
0B
1h
b11111111111111111111000011110000 j
b11111111111111111111000011110000 #
0k
0%
#4000
b11 $
b11111111111111110000000000000000 !
b1111111111111111 "
1e
1d
1c
1b
1]
1\
1[
1Z
0U
0T
0S
0R
0Q
0P
0O
0N
0M
0L
0K
0J
0I
0H
0G
0F
0A
0@
0?
0>
0=
0<
0;
0:
09
08
07
06
1i
b11111111111111111111111111111111 j
b11111111111111111111111111111111 #
#5000
b100 $
b11110000111100000000111100001111 !
b1111111100001111000011111111 "
0]
0\
0[
0Z
1Q
1P
1O
1N
1M
1L
1K
1J
1E
1D
1C
1B
1=
1<
1;
1:
05
04
03
02
0-
0,
0+
0*
0i
0h
1g
b11111111000000001111111111110000 j
b11111111000000001111111111110000 #
#6000
b101 $
b0 !
b11111111111111111111111111111111 "
1]
1\
1[
1Z
1U
1T
1S
1R
1I
1H
1G
1F
0E
0D
0C
0B
0=
0<
0;
0:
01
00
0/
0.
0)
0(
0'
0&
1i
b0 j
b0 #
1k
1%
#7000
b110 $
0i
1h
b1 j
b1 #
0k
0%
#8000
b111 $
b1 !
b11111 "
0`
0_
0^
0]
0\
0[
0Z
0Y
0X
0W
0V
0U
0T
0S
0R
0Q
0P
0O
0N
0M
0L
0K
0J
0I
0H
0G
0F
1E
1i
b10000000000000000000000000000000 j
b10000000000000000000000000000000 #
#9000
b100000 "
0e
0d
0c
0b
0a
1`
b1 j
b1 #
#10000
b1000 $
b10000000000000000000000000000000 !
b11111 "
1e
1d
1c
1b
1a
0`
0E
1&
0i
0h
0g
1f
#11000
b1000000000000000000000000000000 !
1'
0&
b0 j
b0 #
1k
1%
#12000
b1001 $
b10000000000000000000000000000000 !
b1 "
0d
0c
0b
0a
0'
1&
1i
b11000000000000000000000000000000 j
b11000000000000000000000000000000 #
0k
0%
#13000
b1111111111111111111111111111111 !
1E
1D
1C
1B
1A
1@
1?
1>
1=
1<
1;
1:
19
18
17
16
15
14
13
12
11
10
1/
1.
1-
1,
1+
1*
1)
1(
1'
0&
b111111111111111111111111111111 j
b111111111111111111111111111111 #
