register_file.sv
module register_file(
    input logic clk, n_rst, reg_write,
    input logic [4:0] read_reg1, read_reg2, write_reg,
    input logic [31:0] write_data,
    output logic [31:0] read_data1, read_data2
);
    logic [31:0] rf [31:0];

    always_ff @(posedge clk, negedge n_rst) begin
        if(!n_rst) begin
            for (int i =0;i<32;i++) begin
                rf[i] <=32'b0;
            end
        end else if (reg_write && (reg_write !=0)) begin //reg 0 is hardwired to 0
            rf[write_reg] <= write_data;
        end
    end

    assign read_data1 = (read_reg1 == 0) ? 32'b0 : rf[read_reg1]; //reg 0 is hardwired to 0
    assign read_data1 = (read_reg2 == 0) ? 32'b0 : rf[read_reg2]; //reg 0 is hardwired to 0


endmodule

tb_register_file.sv
        `timescale 1ns / 10ps
        /* verilator coverage_off */

        module tb_register_file ();

            localparam CLK_PERIOD = 10ns;
            localparam TIMEOUT    = 1000;

            initial begin
                $dumpfile("waveform.vcd");
                $dumpvars;
            end

            logic clk, n_rst;

            // Clock generator
            always begin
                clk = 0;
                #(CLK_PERIOD / 2.0);
                clk = 1;
                #(CLK_PERIOD / 2.0);
            end

            // DUT interface signals
            logic        reg_write;
            logic [4:0]  read_reg1, read_reg2, write_reg;
            logic [31:0] write_data;
            logic [31:0] read_data1, read_data2;

            // Active-low reset task
            task reset_dut;
            begin
                n_rst = 0;
                @(posedge clk);
                @(posedge clk);
                @(negedge clk);
                n_rst = 1;
                @(negedge clk);
                @(negedge clk);
            end
            endtask
            
            task write_register(
                input logic [4:0]  write_addr,
                input logic [31:0] write_datas
            );
            begin
                @(negedge clk);
                reg_write  = 1'b1;
                write_reg  = write_addr;
                write_data = write_datas;
                @(negedge clk);
                reg_write  = 1'b0;
            end
            endtask

            task read_register(
                input logic [4:0]  read_addr1,
                input logic [4:0]  read_addr2,
                input logic [31:0] exp_1,
                input logic [31:0] exp_2
            );
            begin
                @(negedge clk);
                read_reg1 = read_addr1;
                read_reg2 = read_addr2;
                #1;
                if (read_data1 !== exp_1) begin
                    $display("Expected %08h, got %08h on Port 1 (reg %0d)", exp_1, read_data1, read_addr1);
                end else begin
                    $display("Register %0d returned correct value: %08h", read_addr1, read_data1);
                end

                if (read_data2 !== exp_2) begin
                    $display("Expected %08h, got %08h on Port 2 (reg %0d)", exp_2, read_data2, read_addr2);
                end else begin
                    $display("Register %0d returned correct value: %08h", read_addr2, read_data2);
                end
            end
            endtask

            register_file DUT (
                .clk(clk),
                .n_rst(n_rst),
                .reg_write(reg_write),
                .read_reg1(read_reg1),
                .read_reg2(read_reg2),
                .write_reg(write_reg),
                .write_data(write_data),
                .read_data1(read_data1),
                .read_data2(read_data2)
            );

            initial begin
                // Initialize stimulus lines
                n_rst      = 1'b1;
                reg_write  = 1'b0;
                read_reg1  = '0;
                read_reg2  = '0;
                write_reg  = '0;
                write_data = '0;

                // Apply reset sequence
                reset_dut();

                // Verify all 32 registers retain 0 after reset release
                $display("--- Testing Post-Reset Zero State ---");
                for (int i = 0; i < 32; i = i + 2) begin
                    read_register(5'(i), 5'(i+1), 32'h0, 32'h0);
                end
                
                @(negedge clk);

                $display("--- Testing register zero after write ---");
                write_register(5'd0,32'hFFFF_FFFF);
                read_register(5'd0,5'd0,32'h0,32'h0);

                @(negedge clk);
                $display("--- Testing Indepedent Port ---");
                write_register(5'd1,32'hABCD_DBCA);
                write_register(5'd2,32'hEFDC_BCBC);

                read_register(5'd1,5'd2,32'hABCD_DBCA,32'hEFDC_BCBC);
                read_register(5'd2,5'd1,32'hEFDC_BCBC,32'hABCD_DBCA);

                #(CLK_PERIOD * 2);

                
                $finish;
            end

        endmodule

        /* verilator coverage_on */

waveform.vcd
$date
	Wed Sep 09 21:00:54 2026
$end
$version
	Icarus Verilog
$end
$timescale
	10ps
$end
$scope module tb_register_file $end
$var wire 32 ! read_data2 [31:0] $end
$var wire 32 " read_data1 [31:0] $end
$var real 1 # CLK_PERIOD $end
$var parameter 32 $ TIMEOUT $end
$var reg 1 % clk $end
$var reg 1 & n_rst $end
$var reg 5 ' read_reg1 [4:0] $end
$var reg 5 ( read_reg2 [4:0] $end
$var reg 1 ) reg_write $end
$var reg 32 * write_data [31:0] $end
$var reg 5 + write_reg [4:0] $end
$scope module DUT $end
$var wire 1 % clk $end
$var wire 1 & n_rst $end
$var wire 5 , read_reg1 [4:0] $end
$var wire 5 - read_reg2 [4:0] $end
$var wire 1 ) reg_write $end
$var wire 32 . write_data [31:0] $end
$var wire 5 / write_reg [4:0] $end
$var wire 32 0 read_data2 [31:0] $end
$var wire 32 1 read_data1 [31:0] $end
$scope begin $ivl_for_loop0 $end
$var integer 32 2 i [31:0] $end
$upscope $end
$upscope $end
$scope begin $ivl_for_loop1 $end
$var integer 32 3 i [31:0] $end
$upscope $end
$scope task read_register $end
$var reg 32 4 exp_1 [31:0] $end
$var reg 32 5 exp_2 [31:0] $end
$var reg 5 6 read_addr1 [4:0] $end
$var reg 5 7 read_addr2 [4:0] $end
$upscope $end
$scope task reset_dut $end
$upscope $end
$scope task write_register $end
$var reg 5 8 write_addr [4:0] $end
$var reg 32 9 write_datas [31:0] $end
$upscope $end
$upscope $end
$enddefinitions $end
$comment Show the parameter values. $end
$dumpall
b1111101000 $
r10 #
$end
#0
$dumpvars
bx 9
bx 8
bx 7
bx 6
bx 5
bx 4
b0 3
b100000 2
b0 1
b0 0
b0 /
b0 .
b0 -
b0 ,
b0 +
b0 *
0)
b0 (
b0 '
0&
0%
b0 "
b0 !
$end
#500
b100000 2
1%
#1000
0%
#1500
b100000 2
1%
#2000
1&
0%
#2500
1%
#3000
0%
#3500
1%
#4000
b0 5
b0 4
b1 7
b0 6
0%
#4500
1%
#5000
b1 (
b1 -
0%
#5100
b11 7
b10 6
b10 3
#5500
1%
#6000
b11 (
b11 -
b10 '
b10 ,
0%
#6100
b101 7
b100 6
b100 3
#6500
1%
#7000
b101 (
b101 -
b100 '
b100 ,
0%
#7100
b111 7
b110 6
b110 3
#7500
1%
#8000
b111 (
b111 -
b110 '
b110 ,
0%
#8100
b1001 7
b1000 6
b1000 3
#8500
1%
#9000
b1001 (
b1001 -
b1000 '
b1000 ,
0%
#9100
b1011 7
b1010 6
b1010 3
#9500
1%
#10000
b1011 (
b1011 -
b1010 '
b1010 ,
0%
#10100
b1101 7
b1100 6
b1100 3
#10500
1%
#11000
b1101 (
b1101 -
b1100 '
b1100 ,
0%
#11100
b1111 7
b1110 6
b1110 3
#11500
1%
#12000
b1111 (
b1111 -
b1110 '
b1110 ,
0%
#12100
b10001 7
b10000 6
b10000 3
#12500
1%
#13000
b10001 (
b10001 -
b10000 '
b10000 ,
0%
#13100
b10011 7
b10010 6
b10010 3
#13500
1%
#14000
b10011 (
b10011 -
b10010 '
b10010 ,
0%
#14100
b10101 7
b10100 6
b10100 3
#14500
1%
#15000
b10101 (
b10101 -
b10100 '
b10100 ,
0%
#15100
b10111 7
b10110 6
b10110 3
#15500
1%
#16000
b10111 (
b10111 -
b10110 '
b10110 ,
0%
#16100
b11001 7
b11000 6
b11000 3
#16500
1%
#17000
b11001 (
b11001 -
b11000 '
b11000 ,
0%
#17100
b11011 7
b11010 6
b11010 3
#17500
1%
#18000
b11011 (
b11011 -
b11010 '
b11010 ,
0%
#18100
b11101 7
b11100 6
b11100 3
#18500
1%
#19000
b11101 (
b11101 -
b11100 '
b11100 ,
0%
#19100
b11111 7
b11110 6
b11110 3
#19500
1%
#20000
b11111 (
b11111 -
b11110 '
b11110 ,
0%
#20100
b100000 3
#20500
1%
#21000
b11111111111111111111111111111111 9
b0 8
0%
#21500
1%
#22000
b11111111111111111111111111111111 *
b11111111111111111111111111111111 .
1)
0%
#22500
1%
#23000
b0 7
b0 6
0)
0%
#23500
1%
#24000
b0 (
b0 -
b0 '
b0 ,
0%
#24500
1%
#25000
b10101011110011011101101111001010 9
b1 8
0%
#25500
1%
#26000
b10101011110011011101101111001010 *
b10101011110011011101101111001010 .
b1 +
b1 /
1)
0%
#26500
1%
#27000
b11101111110111001011110010111100 9
b10 8
0)
0%
#27500
1%
#28000
b11101111110111001011110010111100 *
b11101111110111001011110010111100 .
b10 +
b10 /
1)
0%
#28500
1%
#29000
b11101111110111001011110010111100 5
b10101011110011011101101111001010 4
b10 7
b1 6
0)
0%
#29500
1%
#30000
b11101111110111001011110010111100 !
b11101111110111001011110010111100 0
b10101011110011011101101111001010 "
b10101011110011011101101111001010 1
b10 (
b10 -
b1 '
b1 ,
0%
#30100
b10101011110011011101101111001010 5
b11101111110111001011110010111100 4
b1 7
b10 6
#30500
1%
#31000
b10101011110011011101101111001010 !
b10101011110011011101101111001010 0
b11101111110111001011110010111100 "
b11101111110111001011110010111100 1
b1 (
b1 -
b10 '
b10 ,
0%
