source/program_counter.sv
module program_counter(
    input logic clk, n_rst, 
    input logic [1:0] pc_sel, //pc selector
    input logic [31:0] rs1_data, immediate,
    output logic [31:0] pc

);
    localparam logic [1:0] PC_DEFAULT = 2'b00;
    localparam logic [1:0] PC_JALR = 2'b01;
    localparam logic [1:0] PC_TARGET = 2'b10;


    logic [31:0] pc_next;
    logic [31:0] jalr_address;

    assign jalr_address = rs1_data + immediate;
    always_ff @(posedge clk, negedge n_rst) begin
        if(!n_rst) begin
            pc<=32'd0;
        end else begin
            pc<=pc_next;
        end
    end
    always_comb begin
        case(pc_sel)
            PC_JALR: begin
                pc_next={jalr_address[31:1],1'b0}; //LSB of calc target set to 0
            end
            PC_TARGET: begin
                pc_next= pc + immediate;
            end
            default: pc_next=pc+32'd4;
        endcase
        
    end
        
endmodule

testbench/tb_program_couter.sv
        `timescale 1ns / 10ps
        /* verilator coverage_off */

        module tb_program_counter ();

            localparam CLK_PERIOD = 10ns;
            localparam TIMEOUT    = 1000;

            initial begin
                $dumpfile("waveform.vcd");
                $dumpvars;
            end

            logic clk, n_rst;

            // Clock generator
            always begin
                clk = 0;
                #(CLK_PERIOD / 2.0);
                clk = 1;
                #(CLK_PERIOD / 2.0);
            end

            // DUT interface signals
            logic [1:0] pc_sel;
            logic [31:0] rs1_data, immediate;
            logic [31:0] pc;

            localparam logic [1:0] PC_DEFAULT = 2'b00;
            localparam logic [1:0] PC_JALR    = 2'b01;
            localparam logic [1:0] PC_TARGET  = 2'b10;

    
            // Active-low reset task
            task reset_dut;
            begin
                n_rst = 0;
                @(posedge clk);
                @(posedge clk);
                @(negedge clk);
                n_rst = 1;
                @(negedge clk);
                @(negedge clk);
            end
            endtask
            
            
            program_counter DUT (
                .clk(clk),
                .n_rst(n_rst),
                .pc_sel(pc_sel),
                .rs1_data(rs1_data),
                .immediate(immediate),
                .pc(pc)
            );

            function automatic logic [31:0] expected_next_pc(
                input logic [31:0] old_pc,
                input logic [1:0] select,
                input logic [31:0] rs1,
                input logic [31:0] imm
            );
                case(select)
                    PC_JALR: expected_next_pc=(rs1+imm) & 32'hFFFF_FFFE; //sets last bit to 0
                    PC_TARGET: expected_next_pc= old_pc+imm;
                    default: expected_next_pc = old_pc +32'd4;
                endcase
            endfunction
            //test and check task
            task automatic run_test(
                input logic [1:0] test_select,
                input logic [31:0] test_rs1,
                input logic [31:0] test_imm,
                input string testname
            );
                logic [31:0] expected;
                begin
                    @(negedge clk);
                    pc_sel=test_select;
                    rs1_data=test_rs1;
                    immediate=test_imm;
                    expected= expected_next_pc(pc,test_select,test_rs1,test_imm);

                    @(posedge clk); //DUT updates pc
                    #1ns;
                    if(pc!==expected) begin//!== so unknown= fail
                        $display("Failed %s, expected %h, got %h",testname, expected,pc);
                    end else begin
                        $display("Passed %s, expected %h, got %h", testname, expected, pc);
                    end
                end

            endtask

            //CRT
            class pc_transaction;
                rand bit [1:0] select;
                rand bit [31:0] rs1;
                rand int signed offset; //immediate value
                constraint valid_select{
                    select inside{
                        PC_DEFAULT, PC_JALR,PC_TARGET
                    };
                }
                constraint offset_range{
                    offset>=-256;
                    offset<=256;
                }
                constraint target_align{ //constraint doesnt use begin/end
                    if(select==PC_TARGET) 
                        offset %2 ==0;
                    
                }
                constraint selection_distribution {//weight
                    select dist {
                        PC_DEFAULT := 1,
                        PC_JALR    := 1,
                        PC_TARGET  := 1
                    };
                }


            endclass
            property pc_increment;
                @(posedge clk)
                disable iff (!n_rst)
                (pc_sel == PC_DEFAULT) |=>
                (pc == $past(pc) + 32'd4);
            endproperty

            assert property (pc_increment)  
                else $error("PC increment assertion FAILED");
            pc_transaction transaction;
            initial begin
                // Initialize stimulus lines
                n_rst = 1'b1;
                pc_sel=PC_DEFAULT;
                rs1_data=32'd0;
                immediate=32'd0;

                transaction=new();
                // Apply reset sequence
                reset_dut();
                run_test(PC_DEFAULT, 32'd0,32'd0,"Normal PC+4"); //PC+4
                run_test(PC_TARGET, 32'd0,32'd16,"Positive Offset");//offset +16
                run_test(PC_TARGET,32'd0,32'hFFFF_FFF0,"Negative Offset");//offset-16
                run_test(PC_JALR,32'd0,32'h0000_0101,"JALR clear bit 0");
                repeat(100) begin
                    if(!transaction.randomize()) begin
                        $fatal(1,"Transaction randomize failed");
                    end
                    run_test(transaction.select, transaction.rs1,transaction.offset,$sformatf("CRV Select = %b, rs1=%h, offset= %0d", transaction.select,transaction.rs1,transaction.offset));
                    

                end
                $finish;
            end

        endmodule

        /* verilator coverage_on */

questa/waveform.vcd
$date
	Sat Oct 10 19:37:33 2026
$end
$version
	Questa Altera Starter FPGA Edition Version 2025.2
$end
$timescale
	10ps
$end

$scope module tb_program_counter $end
$var parameter 0 ! CLK_PERIOD $end
$var parameter 32 " TIMEOUT $end
$var parameter 2 # PC_DEFAULT $end
$var parameter 2 $ PC_JALR $end
$var parameter 2 % PC_TARGET $end
$var reg 1 & clk $end
$var reg 1 ' n_rst $end
$var reg 2 ( pc_sel [1:0] $end
$var reg 32 ) rs1_data [31:0] $end
$var reg 32 * immediate [31:0] $end
$var reg 32 + pc [31:0] $end

$scope task reset_dut $end
$upscope $end

$scope function expected_next_pc $end
$upscope $end

$scope task run_test $end
$upscope $end

$scope module DUT $end
$var parameter 2 , PC_DEFAULT $end
$var parameter 2 - PC_JALR $end
$var parameter 2 . PC_TARGET $end
$var wire 1 / clk $end
$var wire 1 0 n_rst $end
$var wire 1 1 pc_sel [1] $end
$var wire 1 2 pc_sel [0] $end
$var wire 1 3 rs1_data [31] $end
$var wire 1 4 rs1_data [30] $end
$var wire 1 5 rs1_data [29] $end
$var wire 1 6 rs1_data [28] $end
$var wire 1 7 rs1_data [27] $end
$var wire 1 8 rs1_data [26] $end
$var wire 1 9 rs1_data [25] $end
$var wire 1 : rs1_data [24] $end
$var wire 1 ; rs1_data [23] $end
$var wire 1 < rs1_data [22] $end
$var wire 1 = rs1_data [21] $end
$var wire 1 > rs1_data [20] $end
$var wire 1 ? rs1_data [19] $end
$var wire 1 @ rs1_data [18] $end
$var wire 1 A rs1_data [17] $end
$var wire 1 B rs1_data [16] $end
$var wire 1 C rs1_data [15] $end
$var wire 1 D rs1_data [14] $end
$var wire 1 E rs1_data [13] $end
$var wire 1 F rs1_data [12] $end
$var wire 1 G rs1_data [11] $end
$var wire 1 H rs1_data [10] $end
$var wire 1 I rs1_data [9] $end
$var wire 1 J rs1_data [8] $end
$var wire 1 K rs1_data [7] $end
$var wire 1 L rs1_data [6] $end
$var wire 1 M rs1_data [5] $end
$var wire 1 N rs1_data [4] $end
$var wire 1 O rs1_data [3] $end
$var wire 1 P rs1_data [2] $end
$var wire 1 Q rs1_data [1] $end
$var wire 1 R rs1_data [0] $end
$var wire 1 S immediate [31] $end
$var wire 1 T immediate [30] $end
$var wire 1 U immediate [29] $end
$var wire 1 V immediate [28] $end
$var wire 1 W immediate [27] $end
$var wire 1 X immediate [26] $end
$var wire 1 Y immediate [25] $end
$var wire 1 Z immediate [24] $end
$var wire 1 [ immediate [23] $end
$var wire 1 \ immediate [22] $end
$var wire 1 ] immediate [21] $end
$var wire 1 ^ immediate [20] $end
$var wire 1 _ immediate [19] $end
$var wire 1 ` immediate [18] $end
$var wire 1 a immediate [17] $end
$var wire 1 b immediate [16] $end
$var wire 1 c immediate [15] $end
$var wire 1 d immediate [14] $end
$var wire 1 e immediate [13] $end
$var wire 1 f immediate [12] $end
$var wire 1 g immediate [11] $end
$var wire 1 h immediate [10] $end
$var wire 1 i immediate [9] $end
$var wire 1 j immediate [8] $end
$var wire 1 k immediate [7] $end
$var wire 1 l immediate [6] $end
$var wire 1 m immediate [5] $end
$var wire 1 n immediate [4] $end
$var wire 1 o immediate [3] $end
$var wire 1 p immediate [2] $end
$var wire 1 q immediate [1] $end
$var wire 1 r immediate [0] $end
$var reg 32 s pc [31:0] $end
$var reg 32 t pc_next [31:0] $end
$var reg 32 u jalr_address [31:0] $end
$upscope $end
$upscope $end

$scope begin std $end
$upscope $end
$enddefinitions $end
#0
$dumpvars
0&
0'
b0 (
b0 )
b0 *
b0 +
b0 s
b100 t
b0 u
b1111101000 "
b0 #
b1 $
b10 %
b0 ,
b1 -
b10 .
r10 !
0r
0q
0p
0o
0n
0m
0l
0k
0j
0i
0h
0g
0f
0e
0d
0c
0b
0a
0`
0_
0^
0]
0\
0[
0Z
0Y
0X
0W
0V
0U
0T
0S
0R
0Q
0P
0O
0N
0M
0L
0K
0J
0I
0H
0G
0F
0E
0D
0C
0B
0A
0@
0?
0>
0=
0<
0;
0:
09
08
07
06
05
04
03
02
01
00
0/
$end
#500
1&
1/
#1000
0&
0/
#1500
1&
1/
#2000
0&
0/
1'
10
#2500
1&
1/
b100 s
b100 +
b1000 t
#3000
0&
0/
#3500
1&
1/
b1000 s
b1000 +
b1100 t
#4000
0&
0/
#4500
1&
1/
b1100 s
b1100 +
b10000 t
#5000
0&
0/
#5500
1&
1/
b10000 s
b10000 +
b10100 t
#6000
0&
0/
b10 (
b10000 *
1n
11
b10000 u
b100000 t
#6500
1&
1/
b100000 s
b100000 +
b110000 t
#7000
0&
0/
b11111111111111111111111111110000 *
1m
1l
1k
1j
1i
1h
1g
1f
1e
1d
1c
1b
1a
1`
1_
1^
1]
1\
1[
1Z
1Y
1X
1W
1V
1U
1T
1S
b11111111111111111111111111110000 u
b10000 t
#7500
1&
1/
b10000 s
b10000 +
b0 t
#8000
0&
0/
b1 (
b100000001 *
1r
0n
0m
0l
0k
0i
0h
